bestv_common_util/__init__.py
bestv_common_util/jdbc_util.py
bestv_common_util/kms_util.py
bestv_common_util/lru_cache.py
bestv_common_util/nacos_util.py
bestv_common_util/oss_util.py
bestv_common_util/properties_util.py
bestv_common_util/s3_util.py
bestv_common_util/str_util.py
bestv_common_util/sts_util.py
bestv_common_util/tar_util.py
bestv_common_util-0.3.9.dist-info/LICENSE
bestv_common_util-0.3.9.dist-info/METADATA
bestv_common_util-0.3.9.dist-info/WHEEL
bestv_common_util-0.3.9.dist-info/entry_points.txt
bestv_common_util-0.3.9.dist-info/top_level.txt
bestv_common_util-0.3.9.dist-info/RECORD
