Metadata-Version: 2.1
Name: bestv-common-util
Version: 0.3.9
Summary: Bestv Common Util
Home-page: UNKNOWN
Author: liu.qingchen
Author-email: liu.qingchen@bestv.com.cn
License: MIT
Keywords: bestv_common_util,nacos,kms
Platform: UNKNOWN
Classifier: Development Status :: 3 - Alpha
Classifier: Intended Audience :: Developers
Classifier: Programming Language :: Python :: 3
Classifier: Operating System :: Microsoft :: Windows
Requires-Dist: requests
Requires-Dist: pandas
